other_agents_mcp/__init__.py
other_agents_mcp/cli_manager.py
other_agents_mcp/cli_registry.py
other_agents_mcp/config.py
other_agents_mcp/consensus.py
other_agents_mcp/file_handler.py
other_agents_mcp/logger.py
other_agents_mcp/meeting_api.py
other_agents_mcp/meeting_orchestrator.py
other_agents_mcp/meeting_schema.py
other_agents_mcp/server.py
other_agents_mcp/session_manager.py
other_agents_mcp/sqlite_storage.py
other_agents_mcp/task_manager.py
other_agents_mcp-0.0.8.dist-info/licenses/LICENSE
other_agents_mcp-0.0.8.dist-info/METADATA
other_agents_mcp-0.0.8.dist-info/WHEEL
other_agents_mcp-0.0.8.dist-info/entry_points.txt
other_agents_mcp-0.0.8.dist-info/top_level.txt
other_agents_mcp-0.0.8.dist-info/RECORD
