Metadata-Version: 2.4
Name: other-agents-mcp
Version: 0.0.8
Summary: MCP server for communicating with other AI agents via file-based I/O
Author: Other Agents MCP Contributors
License-Expression: MIT
Project-URL: Homepage, https://github.com/inchan/other-agents
Project-URL: Repository, https://github.com/inchan/other-agents
Project-URL: Issues, https://github.com/inchan/other-agents/issues
Keywords: mcp,ai,agents,claude,gemini,codex,qwen,model-context-protocol
Classifier: Development Status :: 4 - Beta
Classifier: Intended Audience :: Developers
Classifier: Operating System :: OS Independent
Classifier: Programming Language :: Python :: 3
Classifier: Programming Language :: Python :: 3.10
Classifier: Programming Language :: Python :: 3.11
Classifier: Programming Language :: Python :: 3.12
Classifier: Topic :: Software Development :: Libraries :: Python Modules
Classifier: Topic :: Scientific/Engineering :: Artificial Intelligence
Requires-Python: >=3.10
License-File: LICENSE
Requires-Dist: mcp<2.0.0,>=0.9.0
Requires-Dist: PyYAML<7.0,>=6.0
Provides-Extra: dev
Requires-Dist: pytest>=7.4.0; extra == "dev"
Requires-Dist: pytest-cov>=4.1.0; extra == "dev"
Requires-Dist: pytest-asyncio>=0.21.0; extra == "dev"
Requires-Dist: pytest-mock>=3.12.0; extra == "dev"
Requires-Dist: pytest-xdist>=3.5.0; extra == "dev"
Requires-Dist: black>=23.0.0; extra == "dev"
Requires-Dist: ruff>=0.1.0; extra == "dev"
Dynamic: license-file
